eAE/__init__.py
eAE/eAE.py
eae-0.1.3.dist-info/LICENSE
eae-0.1.3.dist-info/METADATA
eae-0.1.3.dist-info/WHEEL
eae-0.1.3.dist-info/top_level.txt
eae-0.1.3.dist-info/RECORD
