Metadata-Version: 2.1
Name: eae
Version: 0.1.3
Summary: Pip package to interact with the eAE-interface
Home-page: https://github.com/aoehmichen/eae-python
Author: Axel Oehmichen
Author-email: axelfrancois.oehmichen11@imperial.ac.uk
License: MIT
Keywords: eAE
Platform: UNKNOWN
Classifier: Environment :: Plugins
Classifier: Intended Audience :: Science/Research
Classifier: License :: OSI Approved :: MIT License
Classifier: Programming Language :: Python
Classifier: Programming Language :: Python :: 3.6
Classifier: Programming Language :: Python :: 3.7
Requires-Dist: requests
Requires-Dist: requests-toolbelt
